py_boost/__init__.py
py_boost/callbacks/__init__.py
py_boost/callbacks/callback.py
py_boost/cv/__init__.py
py_boost/cv/adaptive_es.py
py_boost/cv/base.py
py_boost/cv/cluster_tree.py
py_boost/gpu/__init__.py
py_boost/gpu/base.py
py_boost/gpu/boosting.py
py_boost/gpu/losses/__init__.py
py_boost/gpu/losses/losses.py
py_boost/gpu/losses/metrics.py
py_boost/gpu/losses/multiclass_metrics.py
py_boost/gpu/serialization.py
py_boost/gpu/sketch_boost.py
py_boost/gpu/tree.py
py_boost/gpu/utils.py
py_boost/multioutput/__init__.py
py_boost/multioutput/sketching.py
py_boost/multioutput/target_splitter.py
py_boost/quantization/__init__.py
py_boost/quantization/base.py
py_boost/quantization/utils.py
py_boost/sampling/__init__.py
py_boost/sampling/bagging.py
py_boost/utils/__init__.py
py_boost/utils/logging.py
py_boost/utils/onnx_wrapper.py
py_boost/utils/tl_wrapper.py
py_boost-0.5.2.dist-info/LICENSE
py_boost-0.5.2.dist-info/METADATA
py_boost-0.5.2.dist-info/WHEEL
py_boost-0.5.2.dist-info/RECORD
