Metadata-Version: 2.1
Name: py-boost
Version: 0.5.2
Summary: Python based GBDT
Home-page: https://github.com/sb-ai-lab/Py-Boost
Author: Vakhrushev Anton
Author-email: btbpanda@gmail.com
Requires-Python: >=3.8,<3.14
Classifier: Development Status :: 3 - Alpha
Classifier: Environment :: Console
Classifier: Intended Audience :: Science/Research
Classifier: Natural Language :: English
Classifier: Operating System :: OS Independent
Classifier: Programming Language :: Python :: 3
Classifier: Programming Language :: Python :: 3.8
Classifier: Programming Language :: Python :: 3.9
Classifier: Programming Language :: Python :: 3.10
Classifier: Programming Language :: Python :: 3.11
Classifier: Programming Language :: Python :: 3.10
Classifier: Programming Language :: Python :: 3.11
Classifier: Programming Language :: Python :: 3.12
Classifier: Programming Language :: Python :: 3.13
Classifier: Programming Language :: Python :: 3.8
Classifier: Programming Language :: Python :: 3.9
Classifier: Topic :: Scientific/Engineering :: Artificial Intelligence
Requires-Dist: joblib
Requires-Dist: numba
Requires-Dist: numpy
Requires-Dist: onnx (>=1.16,<2)
Requires-Dist: onnxruntime (>=1.16,<2)
Requires-Dist: pandas (>=1)
Requires-Dist: scikit-learn (>=1)
Requires-Dist: tqdm (>=4.64.1)
Requires-Dist: treelite (>=3,<4)
Requires-Dist: treelite_runtime (>=3,<4)
Requires-Dist: ujson
Project-URL: Repository, https://github.com/sb-ai-lab/Py-Boost
